{"tappeKys":{"code":"tappeKys","emoticon_set":2,"id":0},"tappeWtf":{"code":"tappeWtf","emoticon_set":2,"id":1},"tappeSint":{"code":"tappeSint","emoticon_set":2,"id":2},"tappeLul":{"code":"tappeLul","emoticon_set":2,"id":3},"tappeHue":{"code":"tappeHue","emoticon_set":2,"id":4},"tappeLarve":{"code":"tappeLarve","emoticon_set":2,"id":5},"tappeGrine":{"code":"tappeGrine","emoticon_set":2,"id":6},"tappeCreep":{"code":"tappeCreep","emoticon_set":2,"id":7},"tappeSpæll":{"code":"tappeSpæll","emoticon_set":2,"id":8},"tappeCash":{"code":"tappeCash","emoticon_set":2,"id":9},"tappeLaffen":{"code":"tappeLaffen","emoticon_set":2,"id":10},"tappePog":{"code":"tappePog","emoticon_set":2,"id":11},"tappeAtati":{"code":"tappeAtati","emoticon_set":2,"id":12},"tappeSmug":{"code":"tappeSmug","emoticon_set":2,"id":13},"tappeRage":{"code":"tappeRage","emoticon_set":2,"id":14},"InniVinduet":{"code":"InniVinduet","emoticon_set":2,"id":15}}